jobspy_enhanced/__init__.py
jobspy_enhanced/exception.py
jobspy_enhanced/glassdoor/__init__.py
jobspy_enhanced/glassdoor/constant.py
jobspy_enhanced/glassdoor/util.py
jobspy_enhanced/google/__init__.py
jobspy_enhanced/google/constant.py
jobspy_enhanced/google/util.py
jobspy_enhanced/indeed/__init__.py
jobspy_enhanced/indeed/constant.py
jobspy_enhanced/indeed/util.py
jobspy_enhanced/linkedin/__init__.py
jobspy_enhanced/linkedin/constant.py
jobspy_enhanced/linkedin/util.py
jobspy_enhanced/model.py
jobspy_enhanced/naukri/__init__.py
jobspy_enhanced/naukri/constant.py
jobspy_enhanced/naukri/util.py
jobspy_enhanced/util.py
jobspy_enhanced/ziprecruiter/__init__.py
jobspy_enhanced/ziprecruiter/constant.py
jobspy_enhanced/ziprecruiter/util.py
jobspy_enhanced_scraper-1.0.0.dist-info/METADATA
jobspy_enhanced_scraper-1.0.0.dist-info/WHEEL
jobspy_enhanced_scraper-1.0.0.dist-info/RECORD
