Metadata-Version: 2.4
Name: jobspy-enhanced-scraper
Version: 1.0.0
Summary: Enhanced job scraper for LinkedIn, Indeed, Glassdoor, ZipRecruiter with improved filtering capabilities
Keywords: jobs-scraper,linkedin,indeed,glassdoor,ziprecruiter,naukri,enhanced,filtering
Author: Abhilash RS
Requires-Python: >=3.10,<4.0
Classifier: Programming Language :: Python :: 3
Classifier: Programming Language :: Python :: 3.10
Classifier: Programming Language :: Python :: 3.11
Classifier: Programming Language :: Python :: 3.12
Classifier: Programming Language :: Python :: 3.13
Classifier: Programming Language :: Python :: 3.14
Requires-Dist: NUMPY (==1.26.3)
Requires-Dist: beautifulsoup4 (>=4.12.2,<5.0.0)
Requires-Dist: markdownify (>=1.1.0,<2.0.0)
Requires-Dist: pandas (>=2.1.0,<3.0.0)
Requires-Dist: pydantic (>=2.3.0,<3.0.0)
Requires-Dist: regex (>=2024.4.28,<2025.0.0)
Requires-Dist: requests (>=2.31.0,<3.0.0)
Requires-Dist: tls-client (>=1.0.1,<2.0.0)
Project-URL: Homepage, https://github.com/A6h9lash/jobspy-enhanced-scraper
